rewraa/__init__.py
rewraa/__main__.py
rewraa-1.6.4.dist-info/LICENSE
rewraa-1.6.4.dist-info/METADATA
rewraa-1.6.4.dist-info/WHEEL
rewraa-1.6.4.dist-info/entry_points.txt
rewraa-1.6.4.dist-info/top_level.txt
rewraa-1.6.4.dist-info/RECORD
