Metadata-Version: 2.1
Name: rewraa
Version: 1.6.4
Summary: A Encrypted Chat program
Home-page: UNKNOWN
Author: Javad Shafique
Author-email: javadscript@gmx.com
License: UNKNOWN
Platform: UNKNOWN
Requires-Dist: pycryptodome
